{ "skeleton": { "images": "/Users/khr/Desktop/2.애니메이션/몬스터/M10/images/" },"bones": [	{ "name": "root" }],"slots": [	{ "name": "Leg-F", "bone": "root", "attachment": "Leg-F" },	{ "name": "Leg-B", "bone": "root", "attachment": "Leg-B" },	{ "name": "Boby", "bone": "root", "attachment": "Boby" }],"skins": {	"default": {		"Leg-F": {			"Leg-F": { "x": 325, "y": -396, "width": 60, "height": 72 }		},		"Leg-B": {			"Leg-B": { "x": 196, "y": -399, "width": 60, "height": 72 }		},		"Boby": {			"Boby": { "x": 253, "y": -248.5, "width": 372, "height": 325 }		}	}},"animations": { "animation": {} }}